discovereasy/__init__.py
discovereasy/assumptions.py
discovereasy/main.py
discovereasy/opportunity_tree.py
discovereasy/types.py
discovereasy/templates/graphs.j2.dot
discovereasy-2.1.1.dist-info/METADATA
discovereasy-2.1.1.dist-info/WHEEL
discovereasy-2.1.1.dist-info/entry_points.txt
discovereasy-2.1.1.dist-info/top_level.txt
discovereasy-2.1.1.dist-info/RECORD
