Metadata-Version: 2.1
Name: discovereasy
Version: 2.1.1
Summary: Git-friendly versions of some of the methods from Continuous Discovery Habits
Author-email: Ingo Fruend <github@ingofruend.net>
License: BSD-3-Clause
Keywords: Continuous Discovery Habits
Requires-Dist: typer
Requires-Dist: pydantic
Requires-Dist: rich
Requires-Dist: pyyaml
Requires-Dist: jinja2
